{
  "allDay": [
    {
      "name": "Jude & Steve Joyce",
      "type": "All Day"
    },
    {
      "name": "Amy Joyce & Rob Ilkhan",
      "type": "All Day"
    },
    {
      "name": "Trevor Joyce",
      "type": "All Day"
    },
    {
      "name": "Lynda Joyce",
      "type": "All Day"
    },
    {
      "name": "Lesley Wilkinson",
      "type": "All Day"
    },
    {
      "name": "Ollie & Katy Joyce",
      "type": "All Day"
    },
    {
      "name": "Toby Joyce & Zoe Hammond",
      "type": "All Day"
    },
    {
      "name": "Henry & Victoria Joyce",
      "type": "All Day"
    },
    {
      "name": "Anna & Barney Joyce",
      "type": "All Day"
    },
    {
      "name": "Jenny & Bob Scott",
      "type": "All Day"
    },
    {
      "name": "Helen & Karl Nash",
      "type": "All Day"
    },
    {
      "name": "Avyona & Colin Cripps",
      "type": "All Day"
    },
    {
      "name": "Adriana Radaelli",
      "type": "All Day"
    },
    {
      "name": "Thomas Forgiarini",
      "type": "All Day"
    },
    {
      "name": "Christian Bucci & Teresa De Clara",
      "type": "All Day"
    },
    {
      "name": "Didier Lucotte",
      "type": "All Day"
    },
    {
      "name": "Emi Ho",
      "type": "All Day"
    },
    {
      "name": "Martina Turchetti & Fabio Colosetti",
      "type": "All Day"
    },
    {
      "name": "Alessio Miceli & Elisa Granzotti",
      "type": "All Day"
    },
    {
      "name": "Denise Tajarol",
      "type": "All Day"
    },
    {
      "name": "Jessica Monfredo",
      "type": "All Day"
    },
    {
      "name": "Sara Ferini & Leonardo Loppi",
      "type": "All Day"
    },
    {
      "name": "Michele Zamparini",
      "type": "All Day"
    },
    {
      "name": "Christian & Gabriella De Rosa",
      "type": "All Day"
    },
    {
      "name": "Maoni Ursella & Fabio Facchin",
      "type": "All Day"
    },
    {
      "name": "Eric Tuti & Mateo Lepore",
      "type": "All Day"
    },
    {
      "name": "Becky & Joshua Matthews",
      "type": "All Day"
    },
    {
      "name": "Anna & Peter Verschueren",
      "type": "All Day"
    },
    {
      "name": "Beth & Simeon Smith",
      "type": "All Day"
    },
    {
      "name": "Kate & John Teare",
      "type": "All Day"
    },
    {
      "name": "Becky & Ben Dalglish",
      "type": "All Day"
    },
    {
      "name": "Sue & Graham Smith",
      "type": "All Day"
    },
    {
      "name": "Sarah & Steve Peck",
      "type": "All Day"
    },
    {
      "name": "Shemuel & Nwabisa Redwood-Sawyerr",
      "type": "All Day"
    },
    {
      "name": "Brendon Alford",
      "type": "All Day"
    },
    {
      "name": "Sarah Darnill",
      "type": "All Day"
    },
    {
      "name": "Hannah & David Teren",
      "type": "All Day"
    },
    {
      "name": "Annie & Steve Morris",
      "type": "All Day"
    },
    {
      "name": "Greg & Cheryl Alford",
      "type": "All Day"
      },
      {
      "name": "Nicola Tarver",
      "type": "All Day"
      },
      {
      "name": "Tyrone & Belisha Pillay",
      "type": "All Day"
      },
      {
      "name": "George Rutledge",
      "type": "All Day"
      },
      {
      "name": "Jeanne & Michael Brown",
      "type": "All Day"
      },
      {
      "name": "Joanna Frankwick",
      "type": "All Day"
      },
      {
      "name": "Caitlin & Nick Whelan",
      "type": "All Day"
      },
      {
      "name": "Kelly & Jill Worthington",
      "type": "All Day"
      },
      {
      "name": "Lee Mountney",
      "type": "All Day"
      },
      {
      "name": "Alison & James Curtis",
      "type": "All Day"
      },
      {
      "name": "Mark & Michelle Doyle",
      "type": "All Day"
      },
      {
      "name": "Ross & Hannah Ripamonti",
      "type": "All Day"
      },
      {
      "name": "Ryan & Claudia Ripamonti",
      "type": "All Day"
      },
      {
      "name": "Richard & Zara Ripamonti",
      "type": "All Day"
      },
      {
      "name": "Roderick & Sarah Ripamonti",
      "type": "All Day"
      },
      {
      "name": "Ben & Bonnie Harris",
      "type": "All Day"
      },
      {
      "name": "Robert & Regina Ripamonti",
      "type": "All Day"
      },
      {
      "name": "Kevin & Jocelyne Burridge",
      "type": "All Day"
      },
      {
      "name": "Chris & Carol Staples",
      "type": "All Day"
      },
      {
      "name": "Piet Khumalo",
      "type": "All Day"
      },
      {
      "name": "Sarah & Rob Grinsall",
      "type": "All Day"
      },
      {
      "name": "Hannah Mchugh",
      "type": "All Day"
      },
      {
      "name": "Andrew Ripamonti",
      "type": "All Day"
      },
      {
      "name": "Jaime & Kirsty Macrae",
      "type": "All Day"
      },
      {
      "name": "Jack & Jemima Mullis",
      "type": "All Day"
      },
      {
        "name": "total",
        "type": "Total",
        "count": 107
        }
  ],
  "evening": [
    {
      "name": "Erika & Steve Robertson",
      "children": "",
      "type": "evening"
    },
    {
      "name": "Anna & Neil Gibb",
      "children": "",
      "type": "evening"
    },
    {
      "name": "Sarah Brew",
      "children": "",
      "type": "evening"
    },
    {
      "name": "Ruth & Chris Baker",
      "children": "",
      "type": "evening"
    },
    {
      "name": "Amy & Dave Baker",
      "children": "",
      "type": "evening"
    },
    {
      "name": "Euan & Kaz Macrae",
      "children": "",
      "type": "evening"
    },
    {
      "name": "Holly Macrae",
      "children": "",
      "type": "evening"
    },
    {
      "name": "Cara & Selu Mdalose",
      "children": "",
      "type": "evening"
    },
    {
      "name": "Ewan Griffiths",
      "children": "",
      "type": "evening"
    },
    {
      "name": "Leah & Dave Sherwood",
      "children": "",
      "type": "evening"
    },
    {
      "name": "Megan & Edd Graham",
      "children": "",
      "type": "evening"
    },
    {
      "name": "Megan Stanfield",
      "children": "",
      "type": "evening"
    },
    {
      "name": "Anna & Johnny Knowles",
      "children": "",
      "type": "evening"
    },
    {
      "name": "Nikki Wood",
      "children": "",
      "type": "evening"
    },
    {
      "name": "Dan Scott",
      "children": "",
      "type": "evening"
    },
    {
      "name": "Anna & James Smeed",
      "children": "",
      "type": "evening"
    },
    {
      "name": "Matt & Grace Rees",
      "children": "",
      "type": "evening"
    },
    {
      "name": "Mariose & Emeka Amarikwa",
      "children": "",
      "type": "evening"
    },
    {
      "name": "Beverley & Clem Naidoo",
      "children": "",
      "type": "evening"
    },
    {
      "name": "Simon & Lucy Sheath",
      "children": "",
      "type": "evening"
    },
    {  
      "name": "Maddie & Adrian Porter",
      "children": "",
      "type": "evening"
    },
    {
      "name": "Tiana & Brian Smith",
      "children": "",
      "type": "evening"
    },
    {
      "name": "Elliot Nelson & Micaela Brewerton",
      "children": "",
      "type": "evening"
    },
    {
      "name": "Leighsa Robertson & Jack Lewis",
      "children": "",
      "type": "evening"
    },
    {
      "name": "Marco & Melissa",
      "children": "",
      "type": "evening"
    },
    {
      "name": "Alfonso",
      "children": "",
      "type": "evening"
    },
    {
      "name": "Charlotte Morgan-Jones",
      "children": "",
      "type": "evening"
    },
    {
      "name": "Kathryn Young",
      "children": "",
      "type": "evening"
    },
    {
      "name": "Amy Clarke",
      "children": "",
      "type": "evening"
    },
    {
      "name": "Amy Carswell",
      "children": "",
      "type": "evening"
    },
    {
      "name": "Heather Moore",
      "children": "",
      "type": "evening"
    },
    {
      "name": "Natalie Murphy",
      "children": "",
      "type": "evening"
    },
    {
      "name": "Rosie Fayle",
      "children": "",
      "type": "evening"
    },
    {
      "name": "Fiametta Lenarduzzi",
      "children": "",
      "type": "evening"
    },
    {
      "name": "Claudia Camporese",
      "children": "",
      "type": "evening"
    },
    {
      "name": "Declan Cooper",
      "children": "",
      "type": "evening"
    },
    {
      "name": "Liam Powell",
      "children": "",
      "type": "evening"
    },
    {
      "name": "Geoff & Caron Walton",
      "children": "",
      "type": "evening"
    },
    {
      "name": "Neil & Karyn Dickinson",
      "children": "",
      "type": "evening"
    },
    {
      "name": "Simon & Miriam Williams",
      "children": "",
      "type": "evening"
    },
    {
      "name": "Richard & Jules Sum",
      "children": "",
      "type": "evening"
    },
    {
      "name": "Dan Done",
      "children": "",
      "type": "evening"
    },
    {
      "name": "total",
      "type": "Total",
      "count": 64
      }
  ],
  "ceremony": [
    {
      "name": "Linda Edghill",
      "type": "ceremony"
    },
    {
      "name": "Anne-Marie",
      "type": "ceremony"
    },
    {
      "name": "Jackie Staples",
      "type": "ceremony"
    },
    {
      "name": "Jane Schutt",
      "type": "ceremony"
    },
    {
      "name": "Amy Farrell",
      "type": "ceremony"
    },
    {
      "name": "Kate Gledhill",
      "type": "ceremony"
    },
    {
      "name": "Becky Moore",
      "type": "ceremony"
    },
    {
      "name": "Rachel Brookes",
      "type": "ceremony"
    },
    {
      "name": "Zoe Grundey",
      "type": "ceremony"
    },
    {
      "name": "Noreen Brannigan",
      "type": "ceremony"
    },
    {
      "name": "Chantal Cook",
      "type": "ceremony"
    },
    {
      "name": "Emily Toombes",
      "type": "ceremony"
    },
    {
      "name": "Lola Bryce",
      "type": "ceremony"
    },
    {
      "name": "Matie Viljoen",
      "type": "ceremony"
    },
    {
      "name": "Alice Forster",
      "type": "ceremony"
    },
    {
      "name": "Louise Ashton",
      "type": "ceremony"
    },
    {
      "name": "Kelly Anderson",
      "type": "ceremony"
    },
    {
      "name": "Jacqueline Smith",
      "type": "ceremony"
    },
    {
      "name": "Paula Nicholson",
      "type": "ceremony"
    },
    {
      "name": "Amelia Leech",
      "type": "ceremony"
    },
    {
      "name": "Louise Ridout",
      "type": "ceremony"
    },
    {
      "name": "Jad & Nelius Delange",
      "type": "ceremony"
    },
    {
      "name": "Alex Jones",
      "type": "ceremony"
    },
    {
      "name": "total",
      "type": "Total",
      "count": 24
    }
  ]
}
